{
  "type": "root",
  "children": [
    { "type": "doctype" },
    {
      "type": "element",
      "tagName": "html",
      "properties": {
        "dataHasHydrated": "true",
        "dataTheme": "dark",
        "dataAnnouncementBarInitiallyDismissed": "false",
        "dataRh": "data-has-hydrated,lang,dir",
        "dataMuiColorScheme": "light",
        "lang": "zh-CN",
        "dir": "ltr"
      },
      "children": [
        {
          "type": "element",
          "tagName": "head",
          "properties": {},
          "children": [
            { "type": "text", "value": "\n" },
            {
              "type": "element",
              "tagName": "meta",
              "properties": { "charSet": "UTF-8" },
              "children": []
            },
            { "type": "text", "value": "\n" },
            {
              "type": "element",
              "tagName": "meta",
              "properties": {
                "name": "generator",
                "content": "Docusaurus v3.4.0"
              },
              "children": []
            },
            { "type": "text", "value": "\n" },
            {
              "type": "element",
              "tagName": "title",
              "properties": {},
              "children": [
                { "type": "text", "value": "测试组件😊🚀🎉 | 微课程" }
              ]
            },
            {
              "type": "element",
              "tagName": "link",
              "properties": {
                "rel": ["alternate"],
                "type": "application/rss+xml",
                "href": "/blog/rss.xml",
                "title": "微课程 RSS Feed"
              },
              "children": []
            },
            { "type": "text", "value": "\n" },
            {
              "type": "element",
              "tagName": "link",
              "properties": {
                "rel": ["alternate"],
                "type": "application/atom+xml",
                "href": "/blog/atom.xml",
                "title": "微课程 Atom Feed"
              },
              "children": []
            },
            { "type": "text", "value": "\n\n\n\n" },
            {
              "type": "element",
              "tagName": "link",
              "properties": {
                "rel": ["search"],
                "type": "application/opensearchdescription+xml",
                "title": "微课程",
                "href": "/opensearch.xml"
              },
              "children": []
            },
            { "type": "text", "value": "\n\n\n\n\n\n\n\n" },
            {
              "type": "element",
              "tagName": "link",
              "properties": { "rel": ["icon"], "href": "/img/docusaurus.png" },
              "children": []
            },
            { "type": "text", "value": "\n" },
            {
              "type": "element",
              "tagName": "link",
              "properties": { "rel": ["manifest"], "href": "/manifest.json" },
              "children": []
            },
            { "type": "text", "value": "\n" },
            {
              "type": "element",
              "tagName": "meta",
              "properties": {
                "name": "theme-color",
                "content": "rgb(37, 194, 160)"
              },
              "children": []
            },
            { "type": "text", "value": "\n\n\n" },
            {
              "type": "element",
              "tagName": "script",
              "properties": {
                "src": "/global.js",
                "async": true,
                "defer": true
              },
              "children": []
            },
            { "type": "text", "value": "\n" },
            {
              "type": "element",
              "tagName": "script",
              "properties": {
                "src": "https://hm.baidu.com/hm.js?747b310957305786a9780cedd14587ff",
                "async": true
              },
              "children": []
            },
            { "type": "text", "value": "\n" },
            {
              "type": "element",
              "tagName": "script",
              "properties": {
                "src": "https://polyfill.io/v3/polyfill.min.js?features=Promise%2CObject.entries%2CObject.assign",
                "async": true
              },
              "children": []
            },
            {
              "type": "element",
              "tagName": "link",
              "properties": {
                "rel": ["stylesheet"],
                "href": "/assets/css/styles.b3c0813c.css"
              },
              "children": []
            },
            { "type": "text", "value": "\n" },
            {
              "type": "element",
              "tagName": "script",
              "properties": {
                "src": "/assets/js/runtime~main.eae5adcc.js",
                "defer": true
              },
              "children": []
            },
            { "type": "text", "value": "\n" },
            {
              "type": "element",
              "tagName": "script",
              "properties": {
                "src": "/assets/js/main.56a63836.js",
                "defer": true
              },
              "children": []
            },
            { "type": "text", "value": "\n" },
            {
              "type": "element",
              "tagName": "style",
              "properties": { "type": "text/css" },
              "children": [
                {
                  "type": "text",
                  "value": ".medium-zoom-overlay{position:fixed;top:0;right:0;bottom:0;left:0;opacity:0;transition:opacity .3s;will-change:opacity}.medium-zoom--opened .medium-zoom-overlay{cursor:pointer;cursor:zoom-out;opacity:1}.medium-zoom-image{cursor:pointer;cursor:zoom-in;transition:transform .3s cubic-bezier(.2,0,.2,1)!important}.medium-zoom-image--hidden{visibility:hidden}.medium-zoom-image--opened{position:relative;cursor:pointer;cursor:zoom-out;will-change:transform}"
                }
              ]
            },
            {
              "type": "element",
              "tagName": "style",
              "properties": { "dataEmotion": "css-global", "dataS": "" },
              "children": []
            },
            {
              "type": "element",
              "tagName": "style",
              "properties": { "dataEmotion": "css-global", "dataS": "" },
              "children": []
            },
            {
              "type": "element",
              "tagName": "style",
              "properties": { "dataEmotion": "css-global", "dataS": "" },
              "children": []
            },
            {
              "type": "element",
              "tagName": "style",
              "properties": { "dataEmotion": "css-global", "dataS": "" },
              "children": []
            },
            {
              "type": "element",
              "tagName": "style",
              "properties": { "dataEmotion": "css", "dataS": "" },
              "children": []
            },
            {
              "type": "element",
              "tagName": "link",
              "properties": {
                "rel": ["icon"],
                "href": "/img/favicon.ico",
                "dataRh": "true"
              },
              "children": []
            },
            {
              "type": "element",
              "tagName": "link",
              "properties": {
                "rel": ["canonical"],
                "href": "https://qio.wiki/testpage/",
                "dataRh": "true"
              },
              "children": []
            },
            {
              "type": "element",
              "tagName": "link",
              "properties": {
                "rel": ["alternate"],
                "href": "https://qio.wiki/testpage/",
                "hrefLang": "zh-CN",
                "dataRh": "true"
              },
              "children": []
            },
            {
              "type": "element",
              "tagName": "link",
              "properties": {
                "rel": ["alternate"],
                "href": "https://qio.wiki/testpage/",
                "hrefLang": "x-default",
                "dataRh": "true"
              },
              "children": []
            },
            {
              "type": "element",
              "tagName": "meta",
              "properties": {
                "name": "viewport",
                "content": "width=device-width, initial-scale=1.0",
                "dataRh": "true"
              },
              "children": []
            },
            {
              "type": "element",
              "tagName": "meta",
              "properties": {
                "name": "twitter:card",
                "content": "summary_large_image",
                "dataRh": "true"
              },
              "children": []
            },
            {
              "type": "element",
              "tagName": "meta",
              "properties": {
                "property": "og:url",
                "content": "https://qio.wiki/testpage/",
                "dataRh": "true"
              },
              "children": []
            },
            {
              "type": "element",
              "tagName": "meta",
              "properties": {
                "property": "og:locale",
                "content": "zh_CN",
                "dataRh": "true"
              },
              "children": []
            },
            {
              "type": "element",
              "tagName": "meta",
              "properties": {
                "name": "docusaurus_locale",
                "content": "zh-CN",
                "dataRh": "true"
              },
              "children": []
            },
            {
              "type": "element",
              "tagName": "meta",
              "properties": {
                "name": "docusaurus_tag",
                "content": "default",
                "dataRh": "true"
              },
              "children": []
            },
            {
              "type": "element",
              "tagName": "meta",
              "properties": {
                "name": "docsearch:language",
                "content": "zh-CN",
                "dataRh": "true"
              },
              "children": []
            },
            {
              "type": "element",
              "tagName": "meta",
              "properties": {
                "name": "docsearch:docusaurus_tag",
                "content": "default",
                "dataRh": "true"
              },
              "children": []
            },
            {
              "type": "element",
              "tagName": "meta",
              "properties": {
                "name": "keywords",
                "content": "微课程,基础会计, 课程设计,社交,校园交流,照片",
                "dataRh": "true"
              },
              "children": []
            },
            {
              "type": "element",
              "tagName": "meta",
              "properties": {
                "property": "og:title",
                "content": "测试组件😊🚀🎉 | 微课程",
                "dataRh": "true"
              },
              "children": []
            },
            {
              "type": "element",
              "tagName": "meta",
              "properties": {
                "name": "description",
                "content": "这是一个用于测试的组件，用于演示页面描述的填充。",
                "dataRh": "true"
              },
              "children": []
            },
            {
              "type": "element",
              "tagName": "meta",
              "properties": {
                "property": "og:description",
                "content": "这是一个用于测试的组件，用于演示页面描述的填充。",
                "dataRh": "true"
              },
              "children": []
            },
            {
              "type": "element",
              "tagName": "style",
              "properties": { "dataJss": "", "dataMeta": "makeStyles" },
              "children": [
                {
                  "type": "text",
                  "value": "\n.jss1 {\n  height: 320px;\n  transform: translateZ(0px);\n}\n.jss2 {\n  right: 16px;\n  position: fixed;\n}\n"
                }
              ]
            },
            {
              "type": "element",
              "tagName": "style",
              "properties": { "dataJss": "", "dataMeta": "makeStyles" },
              "children": [{ "type": "text", "value": "\n" }]
            }
          ]
        },
        { "type": "text", "value": "\n" },
        {
          "type": "element",
          "tagName": "body",
          "properties": {
            "className": ["navigation-with-keyboard"],
            "dataRh": "class"
          },
          "children": [
            { "type": "text", "value": "\n" },
            {
              "type": "element",
              "tagName": "script",
              "properties": {},
              "children": [
                {
                  "type": "text",
                  "value": "!function(){function t(t){document.documentElement.setAttribute(\"data-theme\",t)}var e=function(){try{return new URLSearchParams(window.location.search).get(\"docusaurus-theme\")}catch(t){}}()||function(){try{return window.localStorage.getItem(\"theme\")}catch(t){}}();null!==e?t(e):window.matchMedia(\"(prefers-color-scheme: dark)\").matches?t(\"dark\"):window.matchMedia(\"(prefers-color-scheme: light)\").matches?t(\"light\"):t(\"dark\")}(),function(){try{const n=new URLSearchParams(window.location.search).entries();for(var[t,e]of n)if(t.startsWith(\"docusaurus-data-\")){var a=t.replace(\"docusaurus-data-\",\"data-\");document.documentElement.setAttribute(a,e)}}catch(t){}}(),document.documentElement.setAttribute(\"data-announcement-bar-initially-dismissed\",function(){try{return\"true\"===localStorage.getItem(\"docusaurus.announcement.dismiss\")}catch(t){}return!1}())"
                }
              ]
            },
            {
              "type": "element",
              "tagName": "div",
              "properties": { "id": "__docusaurus" },
              "children": [
                {
                  "type": "element",
                  "tagName": "button",
                  "properties": {
                    "className": [
                      "MuiButtonBase-root",
                      "MuiIconButton-root",
                      "MuiIconButton-colorPrimary",
                      "MuiIconButton-sizeMedium",
                      "css-xzarsy"
                    ],
                    "tabIndex": 0,
                    "type": "button",
                    "ariaLabel": "Turn off the light"
                  },
                  "children": [
                    {
                      "type": "element",
                      "tagName": "svg",
                      "properties": {
                        "className": [
                          "MuiSvgIcon-root",
                          "MuiSvgIcon-fontSizeSmall",
                          "css-1k33q06"
                        ],
                        "focusable": "false",
                        "ariaHidden": "true",
                        "viewBox": "0 0 24 24",
                        "dataTestid": "DarkModeOutlinedIcon"
                      },
                      "children": [
                        {
                          "type": "element",
                          "tagName": "path",
                          "properties": {
                            "d": "M9.37 5.51c-.18.64-.27 1.31-.27 1.99 0 4.08 3.32 7.4 7.4 7.4.68 0 1.35-.09 1.99-.27C17.45 17.19 14.93 19 12 19c-3.86 0-7-3.14-7-7 0-2.93 1.81-5.45 4.37-6.49M12 3c-4.97 0-9 4.03-9 9s4.03 9 9 9 9-4.03 9-9c0-.46-.04-.92-.1-1.36-.98 1.37-2.58 2.26-4.4 2.26-2.98 0-5.4-2.42-5.4-5.4 0-1.81.89-3.42 2.26-4.4-.44-.06-.9-.1-1.36-.1"
                          },
                          "children": []
                        }
                      ]
                    },
                    {
                      "type": "element",
                      "tagName": "span",
                      "properties": {
                        "className": ["MuiTouchRipple-root", "css-w0pj6f"]
                      },
                      "children": []
                    }
                  ]
                },
                {
                  "type": "element",
                  "tagName": "div",
                  "properties": {
                    "className": [
                      "MuiContainer-root",
                      "MuiContainer-maxWidthLg",
                      "css-1qsxih2"
                    ]
                  },
                  "children": [
                    {
                      "type": "element",
                      "tagName": "h4",
                      "properties": {
                        "className": [
                          "MuiTypography-root",
                          "MuiTypography-h4",
                          "MuiTypography-gutterBottom",
                          "css-gtvj52"
                        ]
                      },
                      "children": [{ "type": "text", "value": "Todo List" }]
                    },
                    {
                      "type": "element",
                      "tagName": "div",
                      "properties": {
                        "className": [
                          "MuiFormControl-root",
                          "MuiFormControl-marginNormal",
                          "MuiFormControl-fullWidth",
                          "MuiTextField-root",
                          "css-1u0h3mu"
                        ]
                      },
                      "children": [
                        {
                          "type": "element",
                          "tagName": "label",
                          "properties": {
                            "className": [
                              "MuiFormLabel-root",
                              "MuiInputLabel-root",
                              "MuiInputLabel-formControl",
                              "MuiInputLabel-animated",
                              "MuiInputLabel-sizeMedium",
                              "MuiInputLabel-outlined",
                              "MuiFormLabel-colorPrimary",
                              "MuiInputLabel-root",
                              "MuiInputLabel-formControl",
                              "MuiInputLabel-animated",
                              "MuiInputLabel-sizeMedium",
                              "MuiInputLabel-outlined",
                              "css-eas4a2"
                            ],
                            "dataShrink": "false",
                            "htmlFor": [":r1:"],
                            "id": ":r1:-label"
                          },
                          "children": [
                            { "type": "text", "value": "Add a new todo" }
                          ]
                        },
                        {
                          "type": "element",
                          "tagName": "div",
                          "properties": {
                            "className": [
                              "MuiInputBase-root",
                              "MuiOutlinedInput-root",
                              "MuiInputBase-colorPrimary",
                              "MuiInputBase-fullWidth",
                              "MuiInputBase-formControl",
                              "css-1j7j1ks"
                            ]
                          },
                          "children": [
                            {
                              "type": "element",
                              "tagName": "input",
                              "properties": {
                                "ariaInvalid": "false",
                                "id": ":r1:",
                                "type": "text",
                                "className": [
                                  "MuiInputBase-input",
                                  "MuiOutlinedInput-input",
                                  "css-1cov7jk"
                                ],
                                "value": ""
                              },
                              "children": []
                            },
                            {
                              "type": "element",
                              "tagName": "fieldset",
                              "properties": {
                                "ariaHidden": "true",
                                "className": [
                                  "MuiOutlinedInput-notchedOutline",
                                  "css-ke7zsv"
                                ]
                              },
                              "children": [
                                {
                                  "type": "element",
                                  "tagName": "legend",
                                  "properties": { "className": ["css-yjsfm1"] },
                                  "children": [
                                    {
                                      "type": "element",
                                      "tagName": "span",
                                      "properties": {},
                                      "children": [
                                        {
                                          "type": "text",
                                          "value": "Add a new todo"
                                        }
                                      ]
                                    }
                                  ]
                                }
                              ]
                            }
                          ]
                        }
                      ]
                    },
                    {
                      "type": "element",
                      "tagName": "ul",
                      "properties": {
                        "className": [
                          "MuiList-root",
                          "MuiList-padding",
                          "css-1ontqvh"
                        ]
                      },
                      "children": []
                    }
                  ]
                },
                {
                  "type": "element",
                  "tagName": "div",
                  "properties": {},
                  "children": []
                },
                {
                  "type": "element",
                  "tagName": "div",
                  "properties": { "className": ["MuiBox-root", "css-1kfql3i"] },
                  "children": [
                    {
                      "type": "element",
                      "tagName": "div",
                      "properties": {
                        "className": ["MuiBox-root", "css-0"],
                        "id": "urlOverlay",
                        "style": "position: fixed; bottom: 10px; left: 10px; padding: 5px; display: none;"
                      },
                      "children": [
                        {
                          "type": "element",
                          "tagName": "div",
                          "properties": {},
                          "children": [
                            {
                              "type": "text",
                              "value": "https://qio.wiki/testpage"
                            }
                          ]
                        },
                        {
                          "type": "element",
                          "tagName": "canvas",
                          "properties": {
                            "height": 76,
                            "width": 76,
                            "style": "height: 76.2px; width: 76.2px;"
                          },
                          "children": []
                        },
                        { "type": "text", "value": " " }
                      ]
                    },
                    {
                      "type": "element",
                      "tagName": "div",
                      "properties": {
                        "className": [
                          "MuiSpeedDial-root",
                          "MuiSpeedDial-directionUp",
                          "jss2",
                          "jss3",
                          "css-1wpsowf"
                        ],
                        "role": "presentation"
                      },
                      "children": [
                        {
                          "type": "element",
                          "tagName": "div",
                          "properties": {
                            "id": "SpeedDialbasicexample-actions",
                            "role": "menu",
                            "ariaOrientation": "vertical",
                            "className": ["MuiSpeedDial-actions", "css-bknbrw"]
                          },
                          "children": [
                            {
                              "type": "element",
                              "tagName": "button",
                              "properties": {
                                "className": [
                                  "MuiButtonBase-root",
                                  "MuiFab-root",
                                  "MuiFab-circular",
                                  "MuiFab-sizeSmall",
                                  "MuiFab-default",
                                  "MuiFab-root",
                                  "MuiFab-circular",
                                  "MuiFab-sizeSmall",
                                  "MuiFab-default",
                                  "MuiSpeedDialAction-fab",
                                  "css-ekcl9g"
                                ],
                                "tabIndex": -1,
                                "type": "button",
                                "role": "menuitem",
                                "ariaLabel": "collect",
                                "style": "transition-delay: 0ms;"
                              },
                              "children": [
                                {
                                  "type": "element",
                                  "tagName": "svg",
                                  "properties": {
                                    "className": [
                                      "MuiSvgIcon-root",
                                      "MuiSvgIcon-fontSizeMedium",
                                      "css-vubbuv"
                                    ],
                                    "focusable": "false",
                                    "ariaHidden": "true",
                                    "viewBox": "0 0 24 24",
                                    "dataTestid": "FavoriteIcon"
                                  },
                                  "children": [
                                    {
                                      "type": "element",
                                      "tagName": "path",
                                      "properties": {
                                        "d": "m12 21.35-1.45-1.32C5.4 15.36 2 12.28 2 8.5 2 5.42 4.42 3 7.5 3c1.74 0 3.41.81 4.5 2.09C13.09 3.81 14.76 3 16.5 3 19.58 3 22 5.42 22 8.5c0 3.78-3.4 6.86-8.55 11.54z"
                                      },
                                      "children": []
                                    }
                                  ]
                                },
                                {
                                  "type": "element",
                                  "tagName": "span",
                                  "properties": {
                                    "className": [
                                      "MuiTouchRipple-root",
                                      "css-w0pj6f"
                                    ]
                                  },
                                  "children": []
                                }
                              ]
                            },
                            {
                              "type": "element",
                              "tagName": "button",
                              "properties": {
                                "className": [
                                  "MuiButtonBase-root",
                                  "MuiFab-root",
                                  "MuiFab-circular",
                                  "MuiFab-sizeSmall",
                                  "MuiFab-default",
                                  "MuiFab-root",
                                  "MuiFab-circular",
                                  "MuiFab-sizeSmall",
                                  "MuiFab-default",
                                  "MuiSpeedDialAction-fab",
                                  "css-w53kpz"
                                ],
                                "tabIndex": -1,
                                "type": "button",
                                "role": "menuitem",
                                "ariaLabel": "share",
                                "style": "transition-delay: 30ms;"
                              },
                              "children": [
                                {
                                  "type": "element",
                                  "tagName": "svg",
                                  "properties": {
                                    "className": [
                                      "MuiSvgIcon-root",
                                      "MuiSvgIcon-fontSizeMedium",
                                      "css-vubbuv"
                                    ],
                                    "focusable": "false",
                                    "ariaHidden": "true",
                                    "viewBox": "0 0 24 24",
                                    "dataTestid": "ShareIcon"
                                  },
                                  "children": [
                                    {
                                      "type": "element",
                                      "tagName": "path",
                                      "properties": {
                                        "d": "M18 16.08c-.76 0-1.44.3-1.96.77L8.91 12.7c.05-.23.09-.46.09-.7s-.04-.47-.09-.7l7.05-4.11c.54.5 1.25.81 2.04.81 1.66 0 3-1.34 3-3s-1.34-3-3-3-3 1.34-3 3c0 .24.04.47.09.7L8.04 9.81C7.5 9.31 6.79 9 6 9c-1.66 0-3 1.34-3 3s1.34 3 3 3c.79 0 1.5-.31 2.04-.81l7.12 4.16c-.05.21-.08.43-.08.65 0 1.61 1.31 2.92 2.92 2.92 1.61 0 2.92-1.31 2.92-2.92s-1.31-2.92-2.92-2.92"
                                      },
                                      "children": []
                                    }
                                  ]
                                },
                                {
                                  "type": "element",
                                  "tagName": "span",
                                  "properties": {
                                    "className": [
                                      "MuiTouchRipple-root",
                                      "css-w0pj6f"
                                    ]
                                  },
                                  "children": []
                                }
                              ]
                            },
                            {
                              "type": "element",
                              "tagName": "button",
                              "properties": {
                                "className": [
                                  "MuiButtonBase-root",
                                  "MuiFab-root",
                                  "MuiFab-circular",
                                  "MuiFab-sizeSmall",
                                  "MuiFab-default",
                                  "MuiFab-root",
                                  "MuiFab-circular",
                                  "MuiFab-sizeSmall",
                                  "MuiFab-default",
                                  "MuiSpeedDialAction-fab",
                                  "css-5w48ho"
                                ],
                                "tabIndex": -1,
                                "type": "button",
                                "role": "menuitem",
                                "ariaLabel": "comment",
                                "style": "transition-delay: 60ms;"
                              },
                              "children": [
                                {
                                  "type": "element",
                                  "tagName": "svg",
                                  "properties": {
                                    "className": [
                                      "MuiSvgIcon-root",
                                      "MuiSvgIcon-fontSizeMedium",
                                      "css-vubbuv"
                                    ],
                                    "focusable": "false",
                                    "ariaHidden": "true",
                                    "viewBox": "0 0 24 24",
                                    "dataTestid": "CommentIcon"
                                  },
                                  "children": [
                                    {
                                      "type": "element",
                                      "tagName": "path",
                                      "properties": {
                                        "d": "M21.99 4c0-1.1-.89-2-1.99-2H4c-1.1 0-2 .9-2 2v12c0 1.1.9 2 2 2h14l4 4zM18 14H6v-2h12zm0-3H6V9h12zm0-3H6V6h12z"
                                      },
                                      "children": []
                                    }
                                  ]
                                },
                                {
                                  "type": "element",
                                  "tagName": "span",
                                  "properties": {
                                    "className": [
                                      "MuiTouchRipple-root",
                                      "css-w0pj6f"
                                    ]
                                  },
                                  "children": []
                                }
                              ]
                            },
                            {
                              "type": "element",
                              "tagName": "button",
                              "properties": {
                                "className": [
                                  "MuiButtonBase-root",
                                  "MuiFab-root",
                                  "MuiFab-circular",
                                  "MuiFab-sizeSmall",
                                  "MuiFab-default",
                                  "MuiFab-root",
                                  "MuiFab-circular",
                                  "MuiFab-sizeSmall",
                                  "MuiFab-default",
                                  "MuiSpeedDialAction-fab",
                                  "css-1slc8gh"
                                ],
                                "tabIndex": -1,
                                "type": "button",
                                "role": "menuitem",
                                "ariaLabel": "like",
                                "style": "transition-delay: 90ms;"
                              },
                              "children": [
                                {
                                  "type": "element",
                                  "tagName": "svg",
                                  "properties": {
                                    "className": [
                                      "MuiSvgIcon-root",
                                      "MuiSvgIcon-fontSizeMedium",
                                      "css-vubbuv"
                                    ],
                                    "focusable": "false",
                                    "ariaHidden": "true",
                                    "viewBox": "0 0 24 24",
                                    "dataTestid": "ThumbUpIcon"
                                  },
                                  "children": [
                                    {
                                      "type": "element",
                                      "tagName": "path",
                                      "properties": {
                                        "d": "M1 21h4V9H1zm22-11c0-1.1-.9-2-2-2h-6.31l.95-4.57.03-.32c0-.41-.17-.79-.44-1.06L14.17 1 7.59 7.59C7.22 7.95 7 8.45 7 9v10c0 1.1.9 2 2 2h9c.83 0 1.54-.5 1.84-1.22l3.02-7.05c.09-.23.14-.47.14-.73z"
                                      },
                                      "children": []
                                    }
                                  ]
                                },
                                {
                                  "type": "element",
                                  "tagName": "span",
                                  "properties": {
                                    "className": [
                                      "MuiTouchRipple-root",
                                      "css-w0pj6f"
                                    ]
                                  },
                                  "children": []
                                }
                              ]
                            },
                            {
                              "type": "element",
                              "tagName": "button",
                              "properties": {
                                "className": [
                                  "MuiButtonBase-root",
                                  "MuiFab-root",
                                  "MuiFab-circular",
                                  "MuiFab-sizeSmall",
                                  "MuiFab-default",
                                  "MuiFab-root",
                                  "MuiFab-circular",
                                  "MuiFab-sizeSmall",
                                  "MuiFab-default",
                                  "MuiSpeedDialAction-fab",
                                  "css-1qhd0ns"
                                ],
                                "tabIndex": -1,
                                "type": "button",
                                "role": "menuitem",
                                "ariaLabel": "read",
                                "style": "transition-delay: 120ms;"
                              },
                              "children": [
                                {
                                  "type": "element",
                                  "tagName": "svg",
                                  "properties": {
                                    "className": [
                                      "MuiSvgIcon-root",
                                      "MuiSvgIcon-fontSizeMedium",
                                      "css-vubbuv"
                                    ],
                                    "focusable": "false",
                                    "ariaHidden": "true",
                                    "viewBox": "0 0 24 24",
                                    "dataTestid": "VolumeUpIcon"
                                  },
                                  "children": [
                                    {
                                      "type": "element",
                                      "tagName": "path",
                                      "properties": {
                                        "d": "M3 9v6h4l5 5V4L7 9zm13.5 3c0-1.77-1.02-3.29-2.5-4.03v8.05c1.48-.73 2.5-2.25 2.5-4.02M14 3.23v2.06c2.89.86 5 3.54 5 6.71s-2.11 5.85-5 6.71v2.06c4.01-.91 7-4.49 7-8.77s-2.99-7.86-7-8.77"
                                      },
                                      "children": []
                                    }
                                  ]
                                },
                                {
                                  "type": "element",
                                  "tagName": "span",
                                  "properties": {
                                    "className": [
                                      "MuiTouchRipple-root",
                                      "css-w0pj6f"
                                    ]
                                  },
                                  "children": []
                                }
                              ]
                            },
                            {
                              "type": "element",
                              "tagName": "button",
                              "properties": {
                                "className": [
                                  "MuiButtonBase-root",
                                  "MuiFab-root",
                                  "MuiFab-circular",
                                  "MuiFab-sizeSmall",
                                  "MuiFab-default",
                                  "MuiFab-root",
                                  "MuiFab-circular",
                                  "MuiFab-sizeSmall",
                                  "MuiFab-default",
                                  "MuiSpeedDialAction-fab",
                                  "css-1klz0h"
                                ],
                                "tabIndex": -1,
                                "type": "button",
                                "role": "menuitem",
                                "ariaLabel": "follow",
                                "style": "transition-delay: 150ms;"
                              },
                              "children": [
                                {
                                  "type": "element",
                                  "tagName": "svg",
                                  "properties": {
                                    "className": [
                                      "MuiSvgIcon-root",
                                      "MuiSvgIcon-fontSizeMedium",
                                      "css-vubbuv"
                                    ],
                                    "focusable": "false",
                                    "ariaHidden": "true",
                                    "viewBox": "0 0 24 24",
                                    "dataTestid": "PersonAddIcon"
                                  },
                                  "children": [
                                    {
                                      "type": "element",
                                      "tagName": "path",
                                      "properties": {
                                        "d": "M15 12c2.21 0 4-1.79 4-4s-1.79-4-4-4-4 1.79-4 4 1.79 4 4 4m-9-2V7H4v3H1v2h3v3h2v-3h3v-2zm9 4c-2.67 0-8 1.34-8 4v2h16v-2c0-2.66-5.33-4-8-4"
                                      },
                                      "children": []
                                    }
                                  ]
                                },
                                {
                                  "type": "element",
                                  "tagName": "span",
                                  "properties": {
                                    "className": [
                                      "MuiTouchRipple-root",
                                      "css-w0pj6f"
                                    ]
                                  },
                                  "children": []
                                }
                              ]
                            }
                          ]
                        }
                      ]
                    }
                  ]
                }
              ]
            },
            { "type": "text", "value": "\n\n" }
          ]
        }
      ]
    }
  ],
  "data": { "quirksMode": false }
}
